LICENSE
MANIFEST.in
README.md
setup.cfg
setup.py
corpwechat/__init__.py
corpwechat/base.py
corpwechat/config.example.json
corpwechat.egg-info/PKG-INFO
corpwechat.egg-info/SOURCES.txt
corpwechat.egg-info/dependency_links.txt
corpwechat.egg-info/requires.txt
corpwechat.egg-info/top_level.txt